pyfao56v2/__init__.py
pyfao56v2/autoirrigate.py
pyfao56v2/forecast.py
pyfao56v2/irrigation.py
pyfao56v2/main.py
pyfao56v2/model.py
pyfao56v2/parameters.py
pyfao56v2/refet.py
pyfao56v2/weather.py
pyfao56v2/tools/__init__.py
pyfao56v2/tools/euptfv2.py
pyfao56v2/tools/lut.py
pyfao56v2/tools/misc.py
pyfao56v2/tools/pheno.py
pyfao56v2/tools/rosetta.py
pyfao56v2/tools/van_genuchten.py
pyfao56v2/tools/visualization.py
pyfao56v2/tools/euptfv2/list_of_final_PTFs.csv
pyfao56v2/tools/euptfv2/FC_EUHYDI/FC_PTF01.rdata
pyfao56v2/tools/euptfv2/FC_EUHYDI/FC_PTF02.rdata
pyfao56v2/tools/euptfv2/FC_EUHYDI/FC_PTF03.rdata
pyfao56v2/tools/euptfv2/FC_EUHYDI/FC_PTF04.rdata
pyfao56v2/tools/euptfv2/FC_EUHYDI/FC_PTF06.rdata
pyfao56v2/tools/euptfv2/FC_EUHYDI/FC_PTF07.rdata
pyfao56v2/tools/euptfv2/FC_EUHYDI/FC_PTF08.rdata
pyfao56v2/tools/euptfv2/FC_EUHYDI/FC_PTF09.rdata
pyfao56v2/tools/euptfv2/FC_EUHYDI/FC_PTF11.rdata
pyfao56v2/tools/euptfv2/FC_EUHYDI/FC_PTF14.rdata
pyfao56v2/tools/euptfv2/WP_EUHYDI/WP_PTF01.rdata
pyfao56v2/tools/euptfv2/WP_EUHYDI/WP_PTF02.rdata
pyfao56v2/tools/euptfv2/WP_EUHYDI/WP_PTF05.rdata
pyfao56v2/tools/euptfv2/WP_EUHYDI/WP_PTF07.rdata
pyfao56v2/tools/euptfv2/WP_EUHYDI/WP_PTF08.rdata
pyfao56v2/tools/euptfv2/WP_EUHYDI/WP_PTF09.rdata
pyfao56v2/tools/euptfv2/WP_EUHYDI/WP_PTF17.rdata
pyfao56v2/tools/luts/crop.csv
pyfao56v2/tools/luts/irrigation.csv
pyfao56v2/tools/luts/soil.csv
pyfao56v2-0.5.12.dist-info/METADATA
pyfao56v2-0.5.12.dist-info/WHEEL
pyfao56v2-0.5.12.dist-info/licenses/LICENSE
pyfao56v2-0.5.12.dist-info/RECORD
