Metadata-Version: 2.4
Name: pyfao56v2
Version: 0.5.12
Summary: Enhanced pyFAO56 library
Project-URL: Repository, https://github.com/links-ads/guardians-pyfao56
Project-URL: issues, https://github.com/links-ads/guardians-pyfao56/issues
Author-email: Tommaso Monopoli <tommaso.monopoli@linksfoundation.com>
License-File: LICENSE
Keywords: agriculture,crop,evapotranspiration,fao56,irrigation,pyfao56,water
Classifier: License :: OSI Approved :: MIT License
Classifier: Natural Language :: English
Classifier: Operating System :: OS Independent
Classifier: Programming Language :: Python :: 3
Classifier: Topic :: Scientific/Engineering :: Hydrology
Classifier: Topic :: Software Development :: Libraries :: Python Modules
Requires-Python: ~=3.10.0
Requires-Dist: lxml>=5.3.0
Requires-Dist: matplotlib>=3.9.2
Requires-Dist: numpy>=1.26.4
Requires-Dist: openmeteo-requests>=1.3.0
Requires-Dist: openpyxl>=3.1.5
Requires-Dist: pandas>=2.2.3
Requires-Dist: pyyaml>=6.0.2
Requires-Dist: requests-cache>=1.2.1
Requires-Dist: requests>=2.32.3
Requires-Dist: retry-requests>=2.0.0
Requires-Dist: rosetta-soil>=0.1.2
Requires-Dist: urllib3>=2.2.3
Provides-Extra: r
Requires-Dist: rpy2==3.5.1; extra == 'r'
